setup.py
welcomepython/__init__.py
welcomepython.egg-info/PKG-INFO
welcomepython.egg-info/SOURCES.txt
welcomepython.egg-info/dependency_links.txt
welcomepython.egg-info/not-zip-safe
welcomepython.egg-info/top_level.txt