Metadata-Version: 1.0
Name: welcomepython
Version: 0.1
Summary: print message
Home-page: http://github.com/analytics/welcome
Author: Waqas Ali
Author-email: waqas.ali@analytics.com.pk
License: Analytics
Platform: UNKNOWN
